sphinx_guru_builder/__init__.py
sphinx_guru_builder/theme/layout.html
sphinx_guru_builder/theme/theme.conf
sphinx_guru_builder-0.1.2.dist-info/WHEEL
sphinx_guru_builder-0.1.2.dist-info/METADATA
sphinx_guru_builder-0.1.2.dist-info/RECORD
