Metadata-Version: 2.1
Name: sphinx-guru-builder
Version: 0.1.2
Summary: Sphinx Builder for Guru
Home-page: https://github.com/j-martin/sphinx-guru-builder
License: BSD-2
Author: Jean-Martin Archer
Author-email: jm@jmartin.ca
Requires-Python: >=3.6,<4.0
Classifier: License :: Other/Proprietary License
Classifier: Programming Language :: Python :: 3
Classifier: Programming Language :: Python :: 3.6
Classifier: Programming Language :: Python :: 3.7
Classifier: Programming Language :: Python :: 3.8
Classifier: Programming Language :: Python :: 3.9
Requires-Dist: pyaml (>=20.4.0,<21.0.0)
Project-URL: Repository, https://github.com/j-martin/sphinx-guru-builder
